chat_sosal/__init__.py
chat_sosal/chat_sosal.py
chat_sosal/construct/__init__.py
chat_sosal/construct/attachment_handler.py
chat_sosal/construct/message.py
chat_sosal/construct/transcript.py
chat_sosal/construct/assets/__init__.py
chat_sosal/construct/assets/attachment.py
chat_sosal/construct/assets/component.py
chat_sosal/construct/assets/embed.py
chat_sosal/construct/assets/reaction.py
chat_sosal/ext/__init__.py
chat_sosal/ext/cache.py
chat_sosal/ext/discord_import.py
chat_sosal/ext/discord_utils.py
chat_sosal/ext/discriminator.py
chat_sosal/ext/emoji_convert.py
chat_sosal/ext/html_generator.py
chat_sosal/html/__init__.py
chat_sosal/parse/__init__.py
chat_sosal/parse/markdown.py
chat_sosal/parse/mention.py
chat_sosal-2.2.8.dist-info/METADATA
chat_sosal-2.2.8.dist-info/WHEEL
chat_sosal-2.2.8.dist-info/top_level.txt
chat_sosal-2.2.8.dist-info/RECORD
