Metadata-Version: 2.1
Name: chat-sosal
Version: 2.2.8
Summary: sosAl?
Author: feeland
Author-email: prokuronov.valera@mail.ru
Requires-Python: >=3.6
Requires-Dist: aiohttp
Requires-Dist: pytz
Requires-Dist: grapheme
Requires-Dist: emoji
